retrievals/__init__.py
retrievals/version.py
retrievals/data/__init__.py
retrievals/data/collator.py
retrievals/data/dataset.py
retrievals/data/sampler.py
retrievals/data/synthesis/__init__.py
retrievals/data/synthesis/generate_rerank.py
retrievals/data/synthesis/generate_retrieval.py
retrievals/losses/__init__.py
retrievals/losses/arcface.py
retrievals/losses/base.py
retrievals/losses/bce.py
retrievals/losses/bpr.py
retrievals/losses/circle.py
retrievals/losses/colbert_loss.py
retrievals/losses/cosent.py
retrievals/losses/cosine_similarity.py
retrievals/losses/dice.py
retrievals/losses/focal_loss.py
retrievals/losses/infonce.py
retrievals/losses/margin_mse.py
retrievals/losses/mrl_loss.py
retrievals/losses/nt_xcent.py
retrievals/losses/pair_kl.py
retrievals/losses/pearson_loss.py
retrievals/losses/r_drop.py
retrievals/losses/simcse.py
retrievals/losses/token_loss.py
retrievals/losses/triplet.py
retrievals/metrics/__init__.py
retrievals/metrics/evaluation_auto.py
retrievals/metrics/fbeta.py
retrievals/metrics/hit_rate.py
retrievals/metrics/map.py
retrievals/metrics/mrr.py
retrievals/metrics/ndcg.py
retrievals/metrics/similarity.py
retrievals/models/__init__.py
retrievals/models/base.py
retrievals/models/embedding_auto.py
retrievals/models/logits_processor.py
retrievals/models/pooling.py
retrievals/models/rerank.py
retrievals/models/retrieval_auto.py
retrievals/models/utils.py
retrievals/pipelines/__init__.py
retrievals/pipelines/build_hn.py
retrievals/pipelines/embed.py
retrievals/pipelines/graph_rag.py
retrievals/pipelines/llm.py
retrievals/pipelines/long_llm.py
retrievals/pipelines/pretrain.py
retrievals/pipelines/rag.py
retrievals/pipelines/rerank.py
retrievals/pipelines/retrieve.py
retrievals/tools/__init__.py
retrievals/tools/file_ocr.py
retrievals/tools/file_parser.py
retrievals/tools/generator.py
retrievals/tools/langchain.py
retrievals/tools/llama_index.py
retrievals/tools/prompts.py
retrievals/tools/refiner.py
retrievals/tools/rewriter.py
open_retrievals-0.0.14.dist-info/LICENSE
open_retrievals-0.0.14.dist-info/METADATA
open_retrievals-0.0.14.dist-info/WHEEL
open_retrievals-0.0.14.dist-info/top_level.txt
open_retrievals-0.0.14.dist-info/RECORD
