Metadata-Version: 2.1
Name: open-retrievals
Version: 0.0.14
Summary: Text Embeddings for Retrieval and RAG based on transformers
Home-page: https://github.com/LongxingTan/open-retrievals
Author: Longxing Tan
Author-email: tanlongxing888@163.com
License: Apache 2.0 License
Keywords: NLP retrieval RAG rerank text embedding contrastive
Platform: UNKNOWN
Classifier: Development Status :: 5 - Production/Stable
Classifier: Intended Audience :: Developers
Classifier: Intended Audience :: Education
Classifier: Intended Audience :: Science/Research
Classifier: License :: OSI Approved :: Apache Software License
Classifier: Operating System :: OS Independent
Classifier: Programming Language :: Python :: 3
Classifier: Programming Language :: Python :: 3.8
Classifier: Programming Language :: Python :: 3.9
Classifier: Programming Language :: Python :: 3.10
Classifier: Topic :: Scientific/Engineering :: Artificial Intelligence
Requires-Python: >=3.7.0
License-File: LICENSE
Requires-Dist: torch>=1.6.0
Requires-Dist: transformers>=4.0.0
Requires-Dist: tokenizers>=0.14
Requires-Dist: datasets>=1.1.3
Requires-Dist: tqdm>=4.66
Provides-Extra: dev
Requires-Dist: torch>=1.6.0; extra == "dev"
Requires-Dist: transformers>=4.0.0; extra == "dev"
Requires-Dist: tokenizers>=0.14; extra == "dev"
Requires-Dist: datasets>=1.1.3; extra == "dev"
Requires-Dist: tqdm>=4.66; extra == "dev"
Requires-Dist: beir>=2.0.0; extra == "dev"
Requires-Dist: mteb; extra == "dev"
Requires-Dist: C-MTEB>=1.1.0; extra == "dev"
Requires-Dist: mkdocs-material==9.2.8; extra == "dev"
Requires-Dist: mkdocs-awesome-pages-plugin==2.9.2; extra == "dev"
Requires-Dist: mkdocs-jupyter==0.24.7; extra == "dev"
Requires-Dist: faiss-gpu; extra == "dev"
Requires-Dist: peft; extra == "dev"
Requires-Dist: accelerate>=0.20.0; extra == "dev"
Provides-Extra: eval
Requires-Dist: torch>=1.6.0; extra == "eval"
Requires-Dist: transformers>=4.0.0; extra == "eval"
Requires-Dist: tokenizers>=0.14; extra == "eval"
Requires-Dist: datasets>=1.1.3; extra == "eval"
Requires-Dist: tqdm>=4.66; extra == "eval"
Requires-Dist: beir>=2.0.0; extra == "eval"
Requires-Dist: mteb; extra == "eval"
Requires-Dist: C-MTEB>=1.1.0; extra == "eval"
